Workbook

Sheet Tracker
A1: CRT / Aptitude & Reasoning Prep – 9-Week Day-by-Day Tracker
A2: Pardhu – 45–60 min/day, 6 days/week (Sun off). Fill in Date, mark Status, and jot Notes as you go.
A4: Week | B4: Day | C4: Date | D4: Quant Topic | E4: Reasoning Topic | F4: Verbal Task | G4: Time (min) | H4: Status | I4: Notes
A5: Wk 1: Number System | B5: Day 1 | D5: Divisibility rules (2,3,4,5,6,8,9,11) + practice | E5: Blood Relations – basics & family tree diagrams | F5: 10 new words + meanings (start a word list) | G5: 50 | H5: Not Started
A6: Wk 1: Number System | B6: Day 2 | D6: LCM & HCF – basics, methods | E6: Blood Relations – practice, 15 Qs | F6: 10 new words + meanings | G6: 50 | H6: Not Started
A7: Wk 1: Number System | B7: Day 3 | D7: LCM & HCF – word problems | E7: Blood Relations – coded/complex problems | F7: Synonyms practice – 15 Qs | G7: 50 | H7: Not Started
A8: Wk 1: Number System | B8: Day 4 | D8: Remainders – basics, remainder theorem intro | E8: Blood Relations – mixed test, 20 Qs | F8: Antonyms practice – 15 Qs | G8: 50 | H8: Not Started
A9: Wk 1: Number System | B9: Day 5 | D9: Unit digit & cyclicity shortcuts | E9: Coding-Decoding – letter/number basics | F9: Vocabulary revision + 10 new words | G9: 50 | H9: Not Started
A10: Wk 1: Number System | B10: Day 6 | D10: Number System full mock (30 Qs, timed) + review mistakes | E10: Coding-Decoding – practice, 15 Qs | F10: One-word substitution – 15 Qs | G10: 50 | H10: Not Started
A11: Wk 2: Percentages | B11: Day 7 | D11: Percentage basics + memorize fraction-% table (up to 1/12) | E11: Coding-Decoding – advanced patterns | F11: Synonyms – 15 Qs | G11: 50 | H11: Not Started
A12: Wk 2: Percentages | B12: Day 8 | D12: % increase/decrease, successive % change | E12: Coding-Decoding – mixed test, 20 Qs | F12: Antonyms – 15 Qs | G12: 50 | H12: Not Started
A13: Wk 2: Percentages | B13: Day 9 | D13: % applications – population, price change problems | E13: Direction Sense – basics | F13: One-word substitution – 15 Qs | G13: 50 | H13: Not Started
A14: Wk 2: Percentages | B14: Day 10 | D14: Percentage word problems – mixed practice | E14: Direction Sense – practice, 15 Qs | F14: Sentence correction – 15 Qs | G14: 50 | H14: Not Started
A15: Wk 2: Percentages | B15: Day 11 | D15: Percentage mock test (20 Qs) + review | E15: Direction Sense – distance/shortest path problems | F15: Vocabulary revision + 10 new words | G15: 50 | H15: Not Started
A16: Wk 2: Percentages | B16: Day 12 | D16: Number System + Percentage combined revision test (25 Qs) | E16: Direction & Coding mixed test, 20 Qs | F16: Weekly verbal mini-test – 20 Qs | G16: 50 | H16: Not Started
... A58: Wk 9: Full Revision & Mock Tests | B58: Day 54 | D58: Full-length company-pattern mock test #2 + review all weak areas | E58: – included in mock above – | F58: – included in mock above – | G58: 50 | H58: Not Started

Sheet Dashboard
A1: Progress Dashboard
A2: Auto-updates from the Tracker sheet based on the Status column.
A4: Total Days | B4: =COUNTA(Tracker!B5:B58) -> 54 | D4: Week | E4: Days Done | F4: Days Total | G4: % Complete
A5: Done | B5: =COUNTIF(Tracker!H5:H58,"Done") -> 0 | D5: Wk 1: Number System | E5: =COUNTIFS(Tracker!$A$5:$A$58,"Wk 1: Number System",Tracker!$H$5:$H$58,"Done") -> 0 | F5: =COUNTIF(Tracker!$A$5:$A$58,"Wk 1: Number System") -> 6 | G5: =IFERROR(E5/F5,0) -> 0
A6: In Progress | B6: =COUNTIF(Tracker!H5:H58,"In Progress") -> 0 | D6: Wk 2: Percentages | E6: =COUNTIFS(Tracker!$A$5:$A$58,"Wk 2: Percentages",Tracker!$H$5:$H$58,"Done") -> 0 | F6: =COUNTIF(Tracker!$A$5:$A$58,"Wk 2: Percentages") -> 6 | G6: =IFERROR(E6/F6,0) -> 0
A7: Not Started | B7: =COUNTIF(Tracker!H5:H58,"Not Started") -> 54 | D7: Wk 3: Profit/Loss, SI & CI | E7: =COUNTIFS(Tracker!$A$5:$A$58,"Wk 3: Profit/Loss, SI & CI",Tracker!$H$5:$H$58,"Done") -> 0 | F7: =COUNTIF(Tracker!$A$5:$A$58,"Wk 3: Profit/Loss, SI & CI") -> 6 | G7: =IFERROR(E7/F7,0) -> 0
A8: Skipped | B8: =COUNTIF(Tracker!H5:H58,"Skipped") -> 0 | D8: Wk 4: Ratio, Averages, Mixtures | E8: =COUNTIFS(Tracker!$A$5:$A$58,"Wk 4: Ratio, Averages, Mixtures",Tracker!$H$5:$H$58,"Done") -> 0 | F8: =COUNTIF(Tracker!$A$5:$A$58,"Wk 4: Ratio, Averages, Mixtures") -> 6 | G8: =IFERROR(E8/F8,0) -> 0
A9: % Complete | B9: =IFERROR(B5/B4,0) -> 0 | D9: Wk 5: Time & Work, Pipes & Cisterns | E9: =COUNTIFS(Tracker!$A$5:$A$58,"Wk 5: Time & Work, Pipes & Cisterns",Tracker!$H$5:$H$58,"Done") -> 0 | F9: =COUNTIF(Tracker!$A$5:$A$58,"Wk 5: Time & Work, Pipes & Cisterns") -> 6 | G9: =IFERROR(E9/F9,0) -> 0
D10: Wk 6: Time, Speed & Distance | E10: =COUNTIFS(Tracker!$A$5:$A$58,"Wk 6: Time, Speed & Distance",Tracker!$H$5:$H$58,"Done") -> 0 | F10: =COUNTIF(Tracker!$A$5:$A$58,"Wk 6: Time, Speed & Distance") -> 6 | G10: =IFERROR(E10/F10,0) -> 0
D11: Wk 7: Permutation, Combination & Probability | E11: =COUNTIFS(Tracker!$A$5:$A$58,"Wk 7: Permutation, Combination & Probability",Tracker!$H$5:$H$58,"Done") -> 0 | F11: =COUNTIF(Tracker!$A$5:$A$58,"Wk 7: Permutation, Combination & Probability") -> 6 | G11: =IFERROR(E11/F11,0) -> 0
D12: Wk 8: Data Interpretation | E12: =COUNTIFS(Tracker!$A$5:$A$58,"Wk 8: Data Interpretation",Tracker!$H$5:$H$58,"Done") -> 0 | F12: =COUNTIF(Tracker!$A$5:$A$58,"Wk 8: Data Interpretation") -> 6 | G12: =IFERROR(E12/F12,0) -> 0
D13: Wk 9: Full Revision & Mock Tests | E13: =COUNTIFS(Tracker!$A$5:$A$58,"Wk 9: Full Revision & Mock Tests",Tracker!$H$5:$H$58,"Done") -> 0 | F13: =COUNTIF(Tracker!$A$5:$A$58,"Wk 9: Full Revision & Mock Tests") -> 6 | G13: =IFERROR(E13/F13,0) -> 0
A16: How to use
A17: 1. Go to the Tracker sheet and fill in the Date column as you start each day.
A18: 2. Update Status via the dropdown: Not Started / In Progress / Done / Skipped.
A19: 3. This Dashboard recalculates automatically – check it weekly to see your pace.
A20: 4. Use Notes to jot down question types you got wrong, for quick revision later.
A21: 5. If you fall behind, don't skip topics – shift the whole plan forward rather than compress it.
